temp_api/__init__.py
temp_api/__main__.py
temp_api/main.py
temp_api-0.3.0.dist-info/METADATA
temp_api-0.3.0.dist-info/WHEEL
temp_api-0.3.0.dist-info/RECORD
